accounda/__init__.py
accounda/client.py
accounda-0.1.0.dist-info/LICENSE
accounda-0.1.0.dist-info/METADATA
accounda-0.1.0.dist-info/WHEEL
accounda-0.1.0.dist-info/top_level.txt
accounda-0.1.0.dist-info/RECORD
