Metadata-Version: 2.1
Name: accounda
Version: 0.1.0
Summary: A Python library for interaction with the Accounda API.
Home-page: https://github.com/alexander-zotter/accounda-client
Author: Accounda
Author-email: service@accounda.com
Classifier: Programming Language :: Python :: 3
Classifier: License :: OSI Approved :: MIT License
Classifier: Operating System :: OS Independent
Requires-Python: >=3.6
License-File: LICENSE
Requires-Dist: requests >=2.20.0
